LICENSE
README.md
setup.py
earcut/__init__.py
earcut/earcut.py
earcut.egg-info/PKG-INFO
earcut.egg-info/SOURCES.txt
earcut.egg-info/dependency_links.txt
earcut.egg-info/requires.txt
earcut.egg-info/top_level.txt