Metadata-Version: 2.1
Name: earcut
Version: 1.1.1
Summary: A pure Python port of the earcut JS triangulation library
Home-page: https://github.com/MetacitySuite/earcut-python
Author: Metacity
License: ISC
Platform: UNKNOWN
Classifier: License :: OSI Approved :: ISC License (ISCL)
Classifier: Programming Language :: Python :: 3
Classifier: Programming Language :: Python :: 3.8
Requires-Python: >=3.8
License-File: LICENSE
